functionali/__init__.py
functionali/higher_order_functions.py
functionali/predicates.py
functionali/seq_transform.py
functionali/seq_traverse.py
LICENSE
functionali-0.3.0.dist-info/LICENSE
functionali-0.3.0.dist-info/WHEEL
functionali-0.3.0.dist-info/METADATA
functionali-0.3.0.dist-info/RECORD
