Metadata-Version: 2.1
Name: functionali
Version: 0.3.0
Summary: Functional programming tools for python. Putting the fun in functional programming 😉
Home-page: https://functionali.readthedocs.io/en/latest/
License: BSD-3-Clause
Keywords: functional programming,fp,functools
Author: Abhinav Omprakash
Requires-Python: >=3.6,<4.0
Classifier: License :: OSI Approved :: BSD License
Classifier: Programming Language :: Python :: 3
Classifier: Programming Language :: Python :: 3.6
Classifier: Programming Language :: Python :: 3.7
Classifier: Programming Language :: Python :: 3.8
Classifier: Programming Language :: Python :: 3.9
Project-URL: Repository, https://github.com/AbhinavOmprakash/functionali
